gdsplot/__init__.py
gdsplot/_gdsplot.py
gdsplot-0.0.1.dist-info/LICENSE
gdsplot-0.0.1.dist-info/METADATA
gdsplot-0.0.1.dist-info/WHEEL
gdsplot-0.0.1.dist-info/top_level.txt
gdsplot-0.0.1.dist-info/RECORD
