Metadata-Version: 2.1
Name: gdsplot
Version: 0.0.1
Summary: A package to turn gds/oas files into Plotly figures.
Author-email: Carlton Duke <carltondukeatx@gmail.com>
Project-URL: Homepage, https://github.com/carltonduke/gdsplot/
Project-URL: Issues, https://github.com/carltonduke/gdsplot/issues
Classifier: Programming Language :: Python :: 3
Classifier: License :: OSI Approved :: GNU General Public License v3 or later (GPLv3+)
Classifier: Operating System :: OS Independent
Requires-Python: >=3.12
License-File: LICENSE
